cdk_changelog_slack_notify/__init__.py
cdk_changelog_slack_notify/py.typed
cdk_changelog_slack_notify/_jsii/__init__.py
cdk_changelog_slack_notify/_jsii/cdk-changelog-slack-notify@1.74.0.jsii.tgz
cdk_changelog_slack_notify-1.74.0.dist-info/METADATA
cdk_changelog_slack_notify-1.74.0.dist-info/WHEEL
cdk_changelog_slack_notify-1.74.0.dist-info/top_level.txt
cdk_changelog_slack_notify-1.74.0.dist-info/RECORD
