Metadata-Version: 2.1
Name: cdk-changelog-slack-notify
Version: 1.74.0
Summary: A JSII construct lib to deploy a service to send new changes pushed to codecommit to slack channel
Home-page: https://github.com/mikeyangyo/cdk-changelog-slack-notify.git
Author: mikeyangyo<perryvm06vm06@gmail.com>
License: MIT
Project-URL: Source, https://github.com/mikeyangyo/cdk-changelog-slack-notify.git
Platform: UNKNOWN
Classifier: Intended Audience :: Developers
Classifier: Operating System :: OS Independent
Classifier: Programming Language :: JavaScript
Classifier: Programming Language :: Python :: 3 :: Only
Classifier: Programming Language :: Python :: 3.6
Classifier: Programming Language :: Python :: 3.7
Classifier: Programming Language :: Python :: 3.8
Classifier: Typing :: Typed
Classifier: Development Status :: 5 - Production/Stable
Classifier: License :: OSI Approved
Requires-Python: >=3.6
Requires-Dist: aws-cdk.aws-codecommit (==1.74.0)
Requires-Dist: aws-cdk.aws-events-targets (==1.74.0)
Requires-Dist: aws-cdk.aws-iam (==1.74.0)
Requires-Dist: aws-cdk.aws-lambda (==1.74.0)
Requires-Dist: aws-cdk.core (==1.74.0)
Requires-Dist: constructs (<4.0.0,>=3.2.27)
Requires-Dist: jsii (<2.0.0,>=1.15.0)
Requires-Dist: publication (>=0.0.3)
